ndx_pinto_metadata/__init__.py
ndx_pinto_metadata/maze_extension.py
ndx_pinto_metadata/spec/ndx-pinto-metadata.extensions.yaml
ndx_pinto_metadata/spec/ndx-pinto-metadata.namespace.yaml
ndx_pinto_metadata-0.1.2.dist-info/LICENSE.txt
ndx_pinto_metadata-0.1.2.dist-info/METADATA
ndx_pinto_metadata-0.1.2.dist-info/WHEEL
ndx_pinto_metadata-0.1.2.dist-info/top_level.txt
ndx_pinto_metadata-0.1.2.dist-info/RECORD
