Metadata-Version: 2.1
Name: ndx-pinto-metadata
Version: 0.1.2
Summary: The NWB extension for storing ViRMEN experimental metadata for the Pinto lab.
Home-page: 
Author: Szonja Weigl
Author-email: szonja.weigl@catalystneuro.com
License: MIT
Keywords: NeurodataWithoutBorders,NWB,nwb-extension,ndx-extension
Classifier: Intended Audience :: Developers
Classifier: Intended Audience :: Science/Research
Classifier: License :: OSI Approved :: MIT License
License-File: LICENSE.txt
Requires-Dist: pynwb (<3,>=1.5.0)
Requires-Dist: hdmf (<4,>=2.5.6)
